// class version 52.0 (52)
// access flags 0x21
public class LazyFoo {

  // compiled from: newSource1.scala

  @Lscala/reflect/ScalaSignature;(bytes="\u0006\u000113A!\u0001\u0002\u0001\u000b\u00099A*\u0019>z\r>|'\"A\u0002\u0002\u000fq*W\u000e\u001d;z}\r\u00011C\u0001\u0001\u0007!\u00099!\"D\u0001\u0009\u0015\u0005I\u0011!B:dC2\u000c\u0017BA\u0006\u0009\u0005\u0019\u0009e.\u001f*fM\")Q\u0002\u0001C\u0001\u001d\u00051A(\u001b8jiz\"\u0012a\u0004\u0009\u0003!\u0001i\u0011A\u0001\u0005\u0007%\u0001\u0001\u000b\u0015B\n\u0002\u0017\u0011b\u0017M_=gY\u0006<G%\r\u0009\u0003\u000fQI!!\u0006\u0005\u0003\u0007%sG\u000fC\u0004\u0013\u0001\u0001\u0007I\u0011A\u000c\u0016\u0003MAq!\u0007\u0001A\u0002\u0013\u0005!$A\u0008%Y\u0006T\u0018P\u001a7bO\u0012\nt\u000cJ3r)\u0009Yb\u0004\u0005\u0002\u00089%\u0011Q\u0004\u0003\u0002\u0005+:LG\u000fC\u0004 1\u0005\u0005\u0009\u0019A\n\u0002\u0007a$\u0013\u0007\u0003\u0004\"\u0001\u0001\u0006KaE\u0001\u000bM>|GE^1mk\u0016$\u0003bB\u0011\u0001\u0001\u0004%\u0009a\u0006\u0005\u0008I\u0001\u0001\r\u0011\"\u0001&\u000391wn\u001c\u0013wC2,X\rJ0%KF$\"a\u0007\u0014\u0009\u000f}\u0019\u0013\u0011!a\u0001'!9\u0001\u0006AA\u0001\n\u000b9\u0012a\u00014p_\u001e)!F\u0001E\u0001W\u00059A*\u0019>z\r>|\u0007C\u0001\u0009-\r\u0015\u0009!\u0001#\u0001.'\u0009ac\u0001C\u0003\u000eY\u0011\u0005q\u0006F\u0001,\u0011\u0019\u0009D\u0006)Q\u0005'\u0005YA\u0005\\1{s\u001ad\u0017m\u001a\u00133\u0011\u001d\u0009D\u00061A\u0005\u0002]Aq\u0001\u000e\u0017A\u0002\u0013\u0005Q'A\u0008%Y\u0006T\u0018P\u001a7bO\u0012\u0012t\u000cJ3r)\u0009Yb\u0007C\u0004 g\u0005\u0005\u0009\u0019A\n\u0009\rab\u0003\u0015)\u0003:\u0003)\u0011\u0017M\u001d\u0013wC2,X\r\n\u0009\u0003u\u0005s!aO \u0011\u0005qBQ\"A\u001f\u000b\u0005y\"\u0011A\u0002\u001fs_>$h(\u0003\u0002A\u0011\u00051\u0001K]3eK\u001aL!AQ\"\u0003\rM#(/\u001b8h\u0015\u0009\u0001\u0005\u0002C\u00049Y\u0001\u0007I\u0011A#\u0016\u0003eBqa\u0012\u0017A\u0002\u0013\u0005\u0001*\u0001\u0008cCJ$c/\u00197vK\u0012zF%Z9\u0015\u0005mI\u0005bB\u0010G\u0003\u0003\u0005\r!\u000f\u0005\u0008\u00172\n\u0009\u0011\"\u0002F\u0003\r\u0011\u0017M\u001d")

  ATTRIBUTE ScalaSig : unknown

  ATTRIBUTE ScalaInlineInfo : unknown

  // access flags 0x2
  private I $lazyflag$1

  // access flags 0x2
  private I foo$value$

  // access flags 0x9
  public static bar()Ljava/lang/String;
    GETSTATIC LazyFoo$.MODULE$ : LLazyFoo$;
    INVOKEVIRTUAL LazyFoo$.bar ()Ljava/lang/String;
    ARETURN
    MAXSTACK = 1
    MAXLOCALS = 0

  // access flags 0x9
  public static bar$value$_$eq(Ljava/lang/String;)V
    // parameter final  x$1
    GETSTATIC LazyFoo$.MODULE$ : LLazyFoo$;
    ALOAD 0
    INVOKEVIRTUAL LazyFoo$.bar$value$_$eq (Ljava/lang/String;)V
    RETURN
    MAXSTACK = 2
    MAXLOCALS = 1

  // access flags 0x9
  public static bar$value$()Ljava/lang/String;
    GETSTATIC LazyFoo$.MODULE$ : LLazyFoo$;
    INVOKEVIRTUAL LazyFoo$.bar$value$ ()Ljava/lang/String;
    ARETURN
    MAXSTACK = 1
    MAXLOCALS = 0

  // access flags 0x9
  public static $lazyflag$2_$eq(I)V
    // parameter final  x$1
    GETSTATIC LazyFoo$.MODULE$ : LLazyFoo$;
    ILOAD 0
    INVOKEVIRTUAL LazyFoo$.$lazyflag$2_$eq (I)V
    RETURN
    MAXSTACK = 2
    MAXLOCALS = 1

  // access flags 0x9
  public static $lazyflag$2()I
    GETSTATIC LazyFoo$.MODULE$ : LLazyFoo$;
    INVOKEVIRTUAL LazyFoo$.$lazyflag$2 ()I
    IRETURN
    MAXSTACK = 1
    MAXLOCALS = 0

  // access flags 0x11
  public final foo()I
   L0
    LINENUMBER 2 L0
    ALOAD 0
    INVOKEVIRTUAL LazyFoo.$lazyflag$1 ()I
    ICONST_1
    IAND
    ICONST_0
    IF_ICMPEQ L1
    ALOAD 0
    ALOAD 0
    INVOKEVIRTUAL LazyFoo.$lazyflag$1 ()I
    ICONST_1
    IOR
    INVOKEVIRTUAL LazyFoo.$lazyflag$1_$eq (I)V
    ALOAD 0
   L2
    LINENUMBER 3 L2
    ICONST_1
    INVOKEVIRTUAL LazyFoo.foo$value$_$eq (I)V
   L1
    LINENUMBER 2 L1
   FRAME SAME
    ALOAD 0
    INVOKEVIRTUAL LazyFoo.foo$value$ ()I
    IRETURN
   L3
    LOCALVARIABLE this LLazyFoo; L0 L3 0
    MAXSTACK = 3
    MAXLOCALS = 1

  // access flags 0x1
  public <init>()V
   L0
    LINENUMBER 6 L0
    ALOAD 0
    INVOKESPECIAL java/lang/Object.<init> ()V
   L1
    LINENUMBER 2 L1
    ALOAD 0
    ICONST_0
    PUTFIELD LazyFoo.$lazyflag$1 : I
    RETURN
   L2
    LOCALVARIABLE this LLazyFoo; L0 L2 0
    MAXSTACK = 2
    MAXLOCALS = 1
}

