(scala.tools.nsc.Global,scala.tools.nsc.Global$$anon$4)
_root_/analyzer@scala.tools.nsc.Global
_root_/delambdafy$module@scala.tools.nsc.Global/analyzer@scala.tools.nsc.transform.Delambdafy
_root_/lastSeenContext@scala.tools.nsc.Global/$outer@scala.tools.nsc.typechecker.Contexts$Context
_old_/namerFactory$module@scala.tools.nsc.Global$$anon$4/$outer@scala.tools.nsc.typechecker.Analyzer$namerFactory$
_old_/typerFactory$module@scala.tools.nsc.Global$$anon$4/$outer@scala.tools.nsc.typechecker.Analyzer$typerFactory$
_old_/NoImplicitInfo@scala.tools.nsc.Global$$anon$4/$outer@scala.tools.nsc.typechecker.Implicits$ImplicitInfo
_old_/NoContext$module@scala.tools.nsc.Global$$anon$4/$outer@scala.tools.nsc.typechecker.Contexts$Context
_old_/Context$module@scala.tools.nsc.Global$$anon$4/$outer@scala.tools.nsc.typechecker.Contexts$Context$
_root_/lastSeenContext@scala.tools.nsc.Global/scala$tools$nsc$typechecker$Contexts$Context$$_reporter@scala.tools.nsc.typechecker.Contexts$Context/$outer@scala.tools.nsc.typechecker.Contexts$ContextReporter
// class version 52.0 (52)
// access flags 0x31
public final class test/package$ {

  // compiled from: newSource1.scala

  ATTRIBUTE Scala : unknown

  ATTRIBUTE ScalaInlineInfo : unknown

  // access flags 0x9
  public static Ltest/package$; MODULE$

  // access flags 0x12
  private final I boo

  // access flags 0x11
  // signature LFoo<Ljava/lang/Object;>;
  // declaration:  extends Foo<java.lang.Object>
  public final LFoo; local$1

  // access flags 0x9
  public static <clinit>()V
    NEW test/package$
    INVOKESPECIAL test/package$.<init> ()V
    RETURN
    MAXSTACK = 1
    MAXLOCALS = 0

  // access flags 0x1
  public boo()I
   L0
    LINENUMBER 7 L0
    ALOAD 0
    GETFIELD test/package$.boo : I
    IRETURN
   L1
    LOCALVARIABLE this Ltest/package$; L0 L1 0
    MAXSTACK = 1
    MAXLOCALS = 1

  // access flags 0x1
  // signature <A:Ljava/lang/Object;>()LFoo<TA;>;
  // declaration: Foo<A> <A>()
  public get()LFoo;
   L0
    ALOAD 0
    GETFIELD test/package$.local$1 : LFoo;
    ARETURN
   L1
    LOCALVARIABLE this Ltest/package$; L0 L1 0
    MAXSTACK = 1
    MAXLOCALS = 1

  // access flags 0x1
  // signature <A:Ljava/lang/Object;>(TA;)Lscala/collection/immutable/List<TA;>;
  // declaration: scala.collection.immutable.List<A> <A>(A)
  public get1(Ljava/lang/Object;)Lscala/collection/immutable/List;
    // parameter final  a
   L0
    LINENUMBER 11 L0
    GETSTATIC scala/collection/immutable/List$.MODULE$ : Lscala/collection/immutable/List$;
    GETSTATIC scala/Predef$.MODULE$ : Lscala/Predef$;
    ICONST_1
    ANEWARRAY java/lang/Object
    DUP
    ICONST_0
    ALOAD 1
    AASTORE
    INVOKEVIRTUAL scala/Predef$.genericWrapArray (Ljava/lang/Object;)Lscala/collection/mutable/WrappedArray;
    INVOKEVIRTUAL scala/collection/immutable/List$.apply (Lscala/collection/Seq;)Lscala/collection/immutable/List;
    ARETURN
   L1
    LOCALVARIABLE this Ltest/package$; L0 L1 0
    LOCALVARIABLE a Ljava/lang/Object; L0 L1 1
    MAXSTACK = 6
    MAXLOCALS = 2

  // access flags 0x2
  private <init>()V
   L0
    LINENUMBER 13 L0
    ALOAD 0
    INVOKESPECIAL java/lang/Object.<init> ()V
    ALOAD 0
    PUTSTATIC test/package$.MODULE$ : Ltest/package$;
   L1
    LINENUMBER 7 L1
    ALOAD 0
    ICONST_1
    PUTFIELD test/package$.boo : I
   L2
    LINENUMBER 9 L2
    ALOAD 0
    NEW Foo
    DUP
    INVOKESPECIAL Foo.<init> ()V
    PUTFIELD test/package$.local$1 : LFoo;
   L3
    LINENUMBER 6 L3
    RETURN
   L4
    LOCALVARIABLE this Ltest/package$; L0 L4 0
    MAXSTACK = 3
    MAXLOCALS = 1
}

