(scala.tools.nsc.Global,scala.tools.nsc.Global$$anon$4)
_root_/analyzer@scala.tools.nsc.Global
_root_/delambdafy$module@scala.tools.nsc.Global/analyzer@scala.tools.nsc.transform.Delambdafy
_root_/lastSeenContext@scala.tools.nsc.Global/$outer@scala.tools.nsc.typechecker.Contexts$Context
_old_/namerFactory$module@scala.tools.nsc.Global$$anon$4/$outer@scala.tools.nsc.typechecker.Analyzer$namerFactory$
_old_/typerFactory$module@scala.tools.nsc.Global$$anon$4/$outer@scala.tools.nsc.typechecker.Analyzer$typerFactory$
_old_/NoImplicitInfo@scala.tools.nsc.Global$$anon$4/$outer@scala.tools.nsc.typechecker.Implicits$ImplicitInfo
_old_/NoContext$module@scala.tools.nsc.Global$$anon$4/$outer@scala.tools.nsc.typechecker.Contexts$Context
_old_/Context$module@scala.tools.nsc.Global$$anon$4/$outer@scala.tools.nsc.typechecker.Contexts$Context$
_root_/lastSeenContext@scala.tools.nsc.Global/scala$tools$nsc$typechecker$Contexts$Context$$_reporter@scala.tools.nsc.typechecker.Contexts$Context/$outer@scala.tools.nsc.typechecker.Contexts$ContextReporter
// class version 52.0 (52)
// access flags 0x31
// signature LParent<Ljava/lang/String;>;
// declaration:  extends Parent<java.lang.String>
public final class TestStatic$$anon$1 extends Parent  {

  // compiled from: newSource1.scala
  OUTERCLASS TestStatic$ null

  ATTRIBUTE Scala : unknown

  ATTRIBUTE ScalaInlineInfo : unknown
  // access flags 0x11
  public final INNERCLASS TestStatic$$anon$1 null null
  // access flags 0x11
  public final INNERCLASS TestStatic$$anon$3 null null

  // access flags 0x12
  private final I a

  // access flags 0x11
  // signature LFoo<Ljava/lang/Object;>;
  // declaration:  extends Foo<java.lang.Object>
  public final LFoo; local$1

  // access flags 0x1
  public a()I
   L0
    LINENUMBER 11 L0
    ALOAD 0
    GETFIELD TestStatic$$anon$1.a : I
    IRETURN
   L1
    LOCALVARIABLE this LTestStatic$$anon$1; L0 L1 0
    MAXSTACK = 1
    MAXLOCALS = 1

  // access flags 0x11
  // signature <X:Ljava/lang/Object;>()LFoo<Ljava/lang/Object;>;
  // declaration: Foo<java.lang.Object> <X>()
  public final someFunc()LFoo;
   L0
    LINENUMBER 10 L0
    ALOAD 0
    GETFIELD TestStatic$$anon$1.local$1 : LFoo;
    ARETURN
   L1
    LOCALVARIABLE this LTestStatic$$anon$1; L0 L1 0
    MAXSTACK = 1
    MAXLOCALS = 1

  // access flags 0x1
  public <init>()V
   L0
    LINENUMBER 10 L0
    ALOAD 0
    INVOKESPECIAL Parent.<init> ()V
   L1
    LINENUMBER 11 L1
    ALOAD 0
    ICONST_1
    PUTFIELD TestStatic$$anon$1.a : I
   L2
    LINENUMBER 10 L2
    ALOAD 0
    ALOAD 0
    INVOKESPECIAL TestStatic$$anon$3.someFunc ()LFoo;
    PUTFIELD TestStatic$$anon$1.local$1 : LFoo;
    RETURN
   L3
    LOCALVARIABLE this LTestStatic$$anon$1; L0 L3 0
    MAXSTACK = 2
    MAXLOCALS = 1
}

// class version 52.0 (52)
// access flags 0x31
// signature LParent<Ljava/lang/String;>;
// declaration:  extends Parent<java.lang.String>
public final class TestStatic$$anon$2 extends Parent  {

  // compiled from: newSource1.scala
  OUTERCLASS TestStatic$ null

  ATTRIBUTE Scala : unknown

  ATTRIBUTE ScalaInlineInfo : unknown
  // access flags 0x11
  public final INNERCLASS TestStatic$$anon$2 null null
  // access flags 0x11
  public final INNERCLASS TestStatic$$anon$3 null null

  // access flags 0x11
  // signature LFoo<Ljava/lang/Object;>;
  // declaration:  extends Foo<java.lang.Object>
  public final LFoo; local$2

  // access flags 0x11
  // signature <X:Ljava/lang/Object;>()LFoo<Ljava/lang/Object;>;
  // declaration: Foo<java.lang.Object> <X>()
  public final someFunc()LFoo;
   L0
    LINENUMBER 13 L0
    ALOAD 0
    GETFIELD TestStatic$$anon$2.local$2 : LFoo;
    ARETURN
   L1
    LOCALVARIABLE this LTestStatic$$anon$2; L0 L1 0
    MAXSTACK = 1
    MAXLOCALS = 1

  // access flags 0x1
  public <init>()V
   L0
    LINENUMBER 13 L0
    ALOAD 0
    INVOKESPECIAL Parent.<init> ()V
    ALOAD 0
    ALOAD 0
    INVOKESPECIAL TestStatic$$anon$3.someFunc ()LFoo;
    PUTFIELD TestStatic$$anon$2.local$2 : LFoo;
    RETURN
   L1
    LOCALVARIABLE this LTestStatic$$anon$2; L0 L1 0
    MAXSTACK = 2
    MAXLOCALS = 1
}

// class version 52.0 (52)
// access flags 0x31
// signature LParent<Ljava/lang/String;>;
// declaration:  extends Parent<java.lang.String>
public final class TestStatic$$anon$3 extends Parent  {

  // compiled from: newSource1.scala
  OUTERCLASS TestStatic$ null

  ATTRIBUTE Scala : unknown

  ATTRIBUTE ScalaInlineInfo : unknown
  // access flags 0x11
  public final INNERCLASS TestStatic$$anon$3 null null

  // access flags 0x11
  // signature LFoo<Ljava/lang/Object;>;
  // declaration:  extends Foo<java.lang.Object>
  public final LFoo; local$3

  // access flags 0x11
  // signature <X:Ljava/lang/Object;>()LFoo<Ljava/lang/Object;>;
  // declaration: Foo<java.lang.Object> <X>()
  public final someFunc()LFoo;
   L0
    LINENUMBER 17 L0
    ALOAD 0
    GETFIELD TestStatic$$anon$3.local$3 : LFoo;
    ARETURN
   L1
    LOCALVARIABLE this LTestStatic$$anon$3; L0 L1 0
    MAXSTACK = 1
    MAXLOCALS = 1

  // access flags 0x1
  public <init>()V
   L0
    LINENUMBER 17 L0
    ALOAD 0
    INVOKESPECIAL Parent.<init> ()V
    ALOAD 0
    ALOAD 0
    INVOKESPECIAL TestStatic$$anon$3.someFunc ()LFoo;
    PUTFIELD TestStatic$$anon$3.local$3 : LFoo;
    RETURN
   L1
    LOCALVARIABLE this LTestStatic$$anon$3; L0 L1 0
    MAXSTACK = 2
    MAXLOCALS = 1
}

